{
  "creds": {
    "noiseKey": {
      "private": {
        "type": "Buffer",
        "data": "IC2OePC7J7QLMEinmstwQJDC5RzzsLb3RaVW37omymM="
      },
      "public": {
        "type": "Buffer",
        "data": "BVztJMlGsrPgw7/8L3T8rSVs+ZTSDjlpDBtVb3TkcDw="
      }
    },
    "signedIdentityKey": {
      "private": {
        "type": "Buffer",
        "data": "6HU2dXlwjH2JncC4lYMLr19UTYN3EnfP5ISgufU3HmY="
      },
      "public": {
        "type": "Buffer",
        "data": "YQkhjlvF21qpHoisKqxX+UT9W0yxF45X8XvJTEF2iE8="
      }
    },
    "signedPreKey": {
      "keyPair": {
        "private": {
          "type": "Buffer",
          "data": "aGKpH7df52JyA03McBQhxlKmwgu5QsyHuHWbm8q9lWU="
        },
        "public": {
          "type": "Buffer",
          "data": "n3Fr5292+jYSmojZaLzGleccZ/ITJNMyHq2EQ5LznTE="
        }
      },
      "signature": {
        "type": "Buffer",
        "data": "AhWNhZAWOBoWkApi34UBzWvE6tCeRJq8yMG4YMHclT/4vgxlY7ehPB2NQeI/NdgdvF+m4+AX/lAPNo73yS+DDA=="
      },
      "keyId": 1
    },
    "registrationId": 78,
    "advSecretKey": "c5mR1kpI2NVBS0vI2dOWO2V5y9FyI2nRRFPEJD7kXTg=",
    "processedHistoryMessages": [
      {
        "key": {
          "remoteJid": "6281214020357@s.whatsapp.net",
          "fromMe": true,
          "id": "985E481CC1C25EAC55A5F19B43CA0250"
        },
        "timestamp": 1656087001
      }
    ],
    "nextPreKeyId": 32,
    "firstUnuploadedPreKeyId": 32,
    "accountSettings": {
      "unarchiveChats": false
    },
    "account": {
      "details": "CMqw/moQysPXlQYYAQ==",
      "accountSignature": "Zl3YvtMc7E0i3zPy4uwQhjA4w/3n1wxxqEVfLu6WI7VtwMkjkviR3vS4xWM1GSIgYKQzQCe4bzgxAjBo//jDAg==",
      "deviceSignature": "l3mqCeJ+w7FC7UgkPtVGWvIierPBoboSWdigcx6ciF5S+hSadqAb5Inap0sy0oyG7HvTL5FgWXpA7mN4/BMpDw=="
    },
    "me": {
      "id": "6281214020357:1@s.whatsapp.net",
      "name": "DaniBotz",
      "jid": "6281214020357@s.whatsapp.net"
    },
    "signalIdentities": [
      {
        "identifier": {
          "name": "6281214020357:1@s.whatsapp.net",
          "deviceId": 0
        },
        "identifierKey": {
          "type": "Buffer",
          "data": "BeTQkdD4ZaQ5uqoR7e7+C8UyjBHtgSTwf+hIAOBQivFB"
        }
      }
    ],
    "platform": "android",
    "lastAccountSyncTimestamp": 1656087952,
    "myAppStateKeyId": "AAAAAM/Z"
  },
  "keys": {
    "preKeys": {
      "1": {
        "private": {
          "type": "Buffer",
          "data": "wO1G8GlyAP1gaRKs+54M0jHBvUWljx1fWMIfzqFuDlM="
        },
        "public": {
          "type": "Buffer",
          "data": "5mXtd4q8jArZdVOeHNGoxwuVQsz5+B/xgKFnYVLCKHw="
        }
      },
      "2": {
        "private": {
          "type": "Buffer",
          "data": "qN2yPlqVps7SxIP3vTjSvV0cyZzYY6+SUXlRcwa24kU="
        },
        "public": {
          "type": "Buffer",
          "data": "tjDS0mBg/KSvHlVURBvUte1M3L7I4jix8F4fAExsQEc="
        }
      },
      "3": {
        "private": {
          "type": "Buffer",
          "data": "MG90geakEKU38C02BMTnBTLMX1V1jI2Air4qaa8p80o="
        },
        "public": {
          "type": "Buffer",
          "data": "yFLC+77BMkOL8zgWbNAAxOHWEDUbJIvUCbFL6niuB3c="
        }
      },
      "4": {
        "private": {
          "type": "Buffer",
          "data": "aKSSAndm+YuzA+jHyaS8qV5Ip1NBcD5r3aRLRvIzaFM="
        },
        "public": {
          "type": "Buffer",
          "data": "8hL/oTDu6NbAqDtkaApR/QFM+7QSBRxilxjnPLqgcAQ="
        }
      },
      "5": {
        "private": {
          "type": "Buffer",
          "data": "0Ljug9BLxGspla2keKE43J04P+M2tXxwNie/t4xhXGk="
        },
        "public": {
          "type": "Buffer",
          "data": "s4KQp5dSXJTQrmqyXs23meiOHGAO76b5cOL92bTI6gQ="
        }
      },
      "6": {
        "private": {
          "type": "Buffer",
          "data": "wDjk+Il7vy/o9q3F8nXbaLJdvW/o7DVMOKUYvXSWMn4="
        },
        "public": {
          "type": "Buffer",
          "data": "fEBTnwLHTHHlAPbYUo14u/2GFPMKXnZ72nhH/EwyUjk="
        }
      },
      "7": {
        "private": {
          "type": "Buffer",
          "data": "GPPymgudVw1Sq4dI1zIvRgLz0qzGuwq1mwn02IGuE2c="
        },
        "public": {
          "type": "Buffer",
          "data": "239XqKp0KxFkJvriclxOnBDD6PnyuZacSESBqwA98nE="
        }
      },
      "8": {
        "private": {
          "type": "Buffer",
          "data": "WPYLPPIMoTxTaMc2k8e4ang/olsuynQ0cB5MjDie8l8="
        },
        "public": {
          "type": "Buffer",
          "data": "iKgc6v85dcfaixURRlvMbPReOSz6kNxGLekndgQRWXM="
        }
      },
      "9": null,
      "10": {
        "private": {
          "type": "Buffer",
          "data": "oH7qrmNVz4YtI9xYSu6/bRixfxJqtvAHib7uVKdraWo="
        },
        "public": {
          "type": "Buffer",
          "data": "BRXbmJ3ll8niqCo70HqC5A8hpqE+AYpo2FJCzbpvVXU="
        }
      },
      "11": {
        "private": {
          "type": "Buffer",
          "data": "EL0431gNWrjfMNsNFFqaattSYgo+xWwuKq0iEp/spH8="
        },
        "public": {
          "type": "Buffer",
          "data": "tPsy0wFhfOBINFhWcdvZybOaHys9ErnSOoMM/zFwaR8="
        }
      },
      "12": {
        "private": {
          "type": "Buffer",
          "data": "8MMq21FAIwq6yX+CS0vhdzRoJc5VSvIldoMKg1/tp3A="
        },
        "public": {
          "type": "Buffer",
          "data": "NjnhovZXiOuJ/S4QikTbaqaKb9CDhKk197zN+YlGBC8="
        }
      },
      "13": {
        "private": {
          "type": "Buffer",
          "data": "YB0seroz6xHQ8BGmL8uOT6+/82JEg1d714BpIGaMvWI="
        },
        "public": {
          "type": "Buffer",
          "data": "Oc+dut82qJVfsEYA2BgKZ9qNSN5vGhN4HsGORZFOnWY="
        }
      },
      "14": {
        "private": {
          "type": "Buffer",
          "data": "kJlnsq78QLBNlvZ7VbCnPKdnBGv9tGL2ldXu5O9lrUQ="
        },
        "public": {
          "type": "Buffer",
          "data": "E5cgNIE+CoGZJr1anKsCWKmIeSSFEx/7kGNPDg2gfjs="
        }
      },
      "15": null,
      "16": {
        "private": {
          "type": "Buffer",
          "data": "OL1rxlZrKySClRbc0iRV/SpyvcYZ9N1t50wF1jFpX28="
        },
        "public": {
          "type": "Buffer",
          "data": "OJn/f5NVPQAN6ipqUe4rFal84bReBrAwkQSeZpgZch8="
        }
      },
      "17": {
        "private": {
          "type": "Buffer",
          "data": "eIufPOh1FZ7uiVVqqbuEOpbbXsx1IcNSd6/S5THFWGo="
        },
        "public": {
          "type": "Buffer",
          "data": "tXptBYjQsVh4/cOXU2aEzEHY1XjuXwjQolflBh3efFk="
        }
      },
      "18": {
        "private": {
          "type": "Buffer",
          "data": "WMGlDXypSfEuF4N275yr8oeZwIpF1aoDk2Zde4byjXQ="
        },
        "public": {
          "type": "Buffer",
          "data": "6nqIahfRXtHehG/fGiPCfk9EgCEFg9TRA4jsq62hA38="
        }
      },
      "19": null,
      "20": {
        "private": {
          "type": "Buffer",
          "data": "OAnmy2rd0KytcUrP7MDHHdeana66deipLN2QfT9BQmk="
        },
        "public": {
          "type": "Buffer",
          "data": "U/ov0WYFYBsYJL/18igFwPqMG8ZMAuh2OURE1sdwolU="
        }
      },
      "21": {
        "private": {
          "type": "Buffer",
          "data": "MPObDclfWa6+jYtF/Np6nvfUlqCQ8axwB9Hu03Yw834="
        },
        "public": {
          "type": "Buffer",
          "data": "2aiZvZbvUPyzsEGK/CN/tHsn0ifOUrxeKbjKCSgn7B4="
        }
      },
      "22": {
        "private": {
          "type": "Buffer",
          "data": "YB1N41OUEt5seZe0Uqdyxtr/CSMjL4irJUcclJo32UQ="
        },
        "public": {
          "type": "Buffer",
          "data": "x4NaLM3aRSJO61FkObSeaDVCIIPIGqylPUD4H42FVxA="
        }
      },
      "23": {
        "private": {
          "type": "Buffer",
          "data": "GImObNY50wzWxxKVq2Dxq6zMsdiVKUtopve6ESIh/UQ="
        },
        "public": {
          "type": "Buffer",
          "data": "LgZL5GjBLEwlE4Fdq9QoHRGGO3a+bXrWxeQkj/bCvBM="
        }
      },
      "24": {
        "private": {
          "type": "Buffer",
          "data": "8DOwYrdHkXxrzE0pvAXfBlIuwiwJmKtYV3kB7zbe42U="
        },
        "public": {
          "type": "Buffer",
          "data": "yQ3IRwbl30Rj1XqRXZrqTIbZNK96DOhn3Zp/+JHijWc="
        }
      },
      "25": {
        "private": {
          "type": "Buffer",
          "data": "8AvYQI+XqnSoFKvJJff/vJJyySkGt1M4hTLkH4kkNXY="
        },
        "public": {
          "type": "Buffer",
          "data": "6LBHfS+O99xyk0m5EOZdXgWwo23rAppgAEFoU+cZhSE="
        }
      },
      "26": {
        "private": {
          "type": "Buffer",
          "data": "gAmy736ZSkOaUOLneNAcqMYXXtsrxvUdEKDs/1pX7mM="
        },
        "public": {
          "type": "Buffer",
          "data": "ls9Y1T9cOSMI5q5lJfHZS/qVl8WXmp4MdchfyK3x6hE="
        }
      },
      "27": {
        "private": {
          "type": "Buffer",
          "data": "4BU5wVcKDxokiaurYnYRNLJOvZEVgLMLP3kZwAwISHM="
        },
        "public": {
          "type": "Buffer",
          "data": "bs58uPE8loYhI0ZHx0qiy9FA3hhfYvI2qsHG2xlH6Wk="
        }
      },
      "28": {
        "private": {
          "type": "Buffer",
          "data": "UNN3XcvU1eabzXG+uIP1x6MtR0bt+oSRKwp2pKBqxH4="
        },
        "public": {
          "type": "Buffer",
          "data": "TeoYQAkjx+Gis7Xd6BU+Zd/8RpbA8veWLC2HBIN3bg4="
        }
      },
      "29": {
        "private": {
          "type": "Buffer",
          "data": "aHW2A9G+8AGWtR7oqeKM5qoBLHX5FiqDsxZMkcQ0Z0M="
        },
        "public": {
          "type": "Buffer",
          "data": "3LERZBFWoZCO/+7WzIvkl3HkNJH4QEagw8qUcxD76iE="
        }
      },
      "30": {
        "private": {
          "type": "Buffer",
          "data": "GN75T9RMfdjoVT2OP5BDW9oGGcgMHay76+Ej6ccpcUw="
        },
        "public": {
          "type": "Buffer",
          "data": "8zc0UryD+Mm8bsxgheuZRyERiSAXHEPexqpWj0VzXQI="
        }
      },
      "31": {
        "private": {
          "type": "Buffer",
          "data": "oA4nd0Kh4uwzTMifUcq3j2MifIG/5ziKj4W6PirF41g="
        },
        "public": {
          "type": "Buffer",
          "data": "qQf18xxHhaNmfAMxEjrmvMup8UPcrOoTMIm70bC2vVE="
        }
      }
    },
    "sessions": {
      "6281214020357.0": {
        "_sessions": {
          "BTF1CPWceVVjxNrbtl4RBNjbhNv16r5gHsXbbGNwx9I2": {
            "registrationId": 2035469648,
            "currentRatchet": {
              "ephemeralKeyPair": {
                "pubKey": "BabDPUWNPG8bh6uEIQalBR8DFradwehGqZC3Dew33fhZ",
                "privKey": "ELp1SSh/KI7GZJ/G5LEfW4+ccS1fHWA9UYLwz+xz82w="
              },
              "lastRemoteEphemeralKey": "BQ4XYz7Pl12O2FjjFUf6wCk4JpO7BEqNqYAhfCMK7TJb",
              "previousCounter": 0,
              "rootKey": "t616DLfpWAUhfw7Qv2kpZb8pqKQA2RmsnWoAMSGVHm4="
            },
            "indexInfo": {
              "baseKey": "BTF1CPWceVVjxNrbtl4RBNjbhNv16r5gHsXbbGNwx9I2",
              "baseKeyType": 2,
              "closed": -1,
              "used": 1656091743393,
              "created": 1656087903417,
              "remoteIdentityKey": "BeTQkdD4ZaQ5uqoR7e7+C8UyjBHtgSTwf+hIAOBQivFB"
            },
            "_chains": {
              "BXp4sXMhWPj+z5nZCYz3G3dLTxer95UvEHCQ9mX5y2UQ": {
                "chainKey": {
                  "counter": 6
                },
                "chainType": 2,
                "messageKeys": {}
              },
              "BQ4XYz7Pl12O2FjjFUf6wCk4JpO7BEqNqYAhfCMK7TJb": {
                "chainKey": {
                  "counter": 8,
                  "key": "xdKhoBlFwvrNAB+YSAHrpniU6N5sHGfiRHHhnb200UM="
                },
                "chainType": 2,
                "messageKeys": {
                  "7": "i/W6zZFWevqgtKU3Y8ejaKIggOcJ6B0VnKtEuFfUASY="
                }
              },
              "BabDPUWNPG8bh6uEIQalBR8DFradwehGqZC3Dew33fhZ": {
                "chainKey": {
                  "counter": -1,
                  "key": "tGinYq21b7bUtRzeRocCW3n1x/3m832DaBB5xTqc9aE="
                },
                "chainType": 1,
                "messageKeys": {}
              }
            }
          }
        },
        "version": "v1"
      },
      "6281320170984:12.0": {
        "_sessions": {
          "BaEgw3JYa5M3qpa2BlP2nImc6Jl9E3aMUiBdvBTSw34O": {
            "registrationId": 3354,
            "currentRatchet": {
              "ephemeralKeyPair": {
                "pubKey": "BWk8cChR2BK0MUyv56Y8X5sXLAi7cKblpSt3CwhRP2Ea",
                "privKey": "WNd6KaQDTPu3Ek6VoU88+yqHrAzkuvi4XQHAks4Qi3Y="
              },
              "lastRemoteEphemeralKey": "BdxfY/9erAVcOKT341VmvzSmz3DIQDuxr5qjmd3uBq05",
              "previousCounter": 0,
              "rootKey": "0codGJDktjd+Om7d/9mLO3Q71/Tt/MC6y3idMjeUvfs="
            },
            "indexInfo": {
              "baseKey": "BaEgw3JYa5M3qpa2BlP2nImc6Jl9E3aMUiBdvBTSw34O",
              "baseKeyType": 1,
              "closed": -1,
              "used": 1656087910723,
              "created": 1656087910723,
              "remoteIdentityKey": "Ba3mtaPk8jg+LG7FYEYnnaKvU8aeh4+w7A96S0r7hJsE"
            },
            "_chains": {
              "BWk8cChR2BK0MUyv56Y8X5sXLAi7cKblpSt3CwhRP2Ea": {
                "chainKey": {
                  "counter": 0,
                  "key": "Pn8nkmcNYkEU4gRRu5wU2yJg9dlEUTJtxqPnQQGIBHI="
                },
                "chainType": 1,
                "messageKeys": {}
              }
            },
            "pendingPreKey": {
              "signedKeyId": 1,
              "baseKey": "BaEgw3JYa5M3qpa2BlP2nImc6Jl9E3aMUiBdvBTSw34O"
            }
          }
        },
        "version": "v1"
      },
      "6281320170984.0": {
        "_sessions": {
          "Bbt+F+BOYbciQerDWB+zn/YtuWkDYg2DcHK/j+YD0VMr": {
            "registrationId": 744665182,
            "currentRatchet": {
              "ephemeralKeyPair": {
                "pubKey": "BXzHhXHwh/Inru4ShxeYQr30B9sJp1qtqjo9MN5ErLQs",
                "privKey": "0AV6lj/8ullctMk/QxVNy5OHdG1AGH4mCSizj0tc11I="
              },
              "lastRemoteEphemeralKey": "BfA0RT6CwDESm8qTsWReWJ2HeA2/pGee8nCGoMyhcN0d",
              "previousCounter": 0,
              "rootKey": "vKt9jfrEwKAYpVwNvH/YD5ogxkFpTCT4X6sY8+pg3yI="
            },
            "indexInfo": {
              "baseKey": "Bbt+F+BOYbciQerDWB+zn/YtuWkDYg2DcHK/j+YD0VMr",
              "baseKeyType": 1,
              "closed": 1656087913429,
              "used": 1656087910802,
              "created": 1656087910802,
              "remoteIdentityKey": "BdIbVVo0jk9vdR5pM6o5RHOzOCQU3xERGxUokyVDZGFc"
            },
            "_chains": {
              "BXzHhXHwh/Inru4ShxeYQr30B9sJp1qtqjo9MN5ErLQs": {
                "chainKey": {
                  "counter": 0,
                  "key": "PACaPKZUnCgmubepm4XoedE5CkVJlUCkbmMNJ4Pvz14="
                },
                "chainType": 1,
                "messageKeys": {}
              }
            },
            "pendingPreKey": {
              "signedKeyId": 1,
              "baseKey": "Bbt+F+BOYbciQerDWB+zn/YtuWkDYg2DcHK/j+YD0VMr",
              "preKeyId": 13628448
            }
          },
          "BZb0ucmnuF3DIgupg2Lnhl+Onmf/CZ1vNP9fx33rLME1": {
            "registrationId": 744665182,
            "currentRatchet": {
              "ephemeralKeyPair": {
                "pubKey": "Bb9fz+oMAtN+DEJfWgQhPUOnaGmeqGSwXaTXkXq/TSQN",
                "privKey": "iNq1ma1dX9NN47jqlSw+ZH1L142Ut4MhXri+KRLMHms="
              },
              "lastRemoteEphemeralKey": "BfA0RT6CwDESm8qTsWReWJ2HeA2/pGee8nCGoMyhcN0d",
              "previousCounter": 0,
              "rootKey": "4URyvF7+KPv2UvsT2WA6X9yuBxw6TYxd4OXkU6HprjM="
            },
            "indexInfo": {
              "baseKey": "BZb0ucmnuF3DIgupg2Lnhl+Onmf/CZ1vNP9fx33rLME1",
              "baseKeyType": 1,
              "closed": 1656089400903,
              "used": 1656087913404,
              "created": 1656087913404,
              "remoteIdentityKey": "BdIbVVo0jk9vdR5pM6o5RHOzOCQU3xERGxUokyVDZGFc"
            },
            "_chains": {
              "Bb9fz+oMAtN+DEJfWgQhPUOnaGmeqGSwXaTXkXq/TSQN": {
                "chainKey": {
                  "counter": -1,
                  "key": "aaf/npRFNEGhCrpu6u66T9X2OzPR57o7uK6oQvENaY0="
                },
                "chainType": 1,
                "messageKeys": {}
              }
            },
            "pendingPreKey": {
              "signedKeyId": 1,
              "baseKey": "BZb0ucmnuF3DIgupg2Lnhl+Onmf/CZ1vNP9fx33rLME1",
              "preKeyId": 13628430
            }
          },
          "BcEEvSItGwCFJz1ENwR7pLMgV8ouLfA3ur70QUVZkFQz": {
            "registrationId": 744665182,
            "currentRatchet": {
              "ephemeralKeyPair": {
                "pubKey": "BTO+CBDAqGgFHjwJdnykiOnFr87Y09g0cVY8OJDxnZEt",
                "privKey": "4FYwr2rW9X3KwTi/vTdIPlvLkIFQ1tvFIf+MPR2EGkY="
              },
              "lastRemoteEphemeralKey": "BQNGgfr76V17hUs5rhbFfK+MlWxI4gLimPWIrnbdgy9g",
              "previousCounter": 0,
              "rootKey": "Zn4pxQ8SFVRUwEt6Uf05aNgOIJVeLbtrq9Cdr52zvZE="
            },
            "indexInfo": {
              "baseKey": "BcEEvSItGwCFJz1ENwR7pLMgV8ouLfA3ur70QUVZkFQz",
              "baseKeyType": 2,
              "closed": -1,
              "used": 1656089400965,
              "created": 1656089400964,
              "remoteIdentityKey": "BdIbVVo0jk9vdR5pM6o5RHOzOCQU3xERGxUokyVDZGFc"
            },
            "_chains": {
              "BQNGgfr76V17hUs5rhbFfK+MlWxI4gLimPWIrnbdgy9g": {
                "chainKey": {
                  "counter": 1,
                  "key": "G0zzOEOystar3whtZslmThFr3urIiPpPUdRnQzHpxrw="
                },
                "chainType": 2,
                "messageKeys": {}
              },
              "BTO+CBDAqGgFHjwJdnykiOnFr87Y09g0cVY8OJDxnZEt": {
                "chainKey": {
                  "counter": -1,
                  "key": "Qmjgl+x2ArBXJlJGiG2Ke8IxvaLgxrCI18l7Bh6jTR4="
                },
                "chainType": 1,
                "messageKeys": {}
              }
            }
          }
        },
        "version": "v1"
      },
      "6281251549899.0": {
        "_sessions": {
          "BSnSXwPlFucsvHCzqECLOQVM9Bit/sU6UWEEepgYTsJj": {
            "registrationId": 1255787210,
            "currentRatchet": {
              "ephemeralKeyPair": {
                "pubKey": "Be8h21fUYM1FxSXWO9pZLDME1jhCzN5FVvML88txXJka",
                "privKey": "eASNGa77YiADviv0K6Jltr6h7dbyTQHfgLUftDOfH3Y="
              },
              "lastRemoteEphemeralKey": "BbjynG4Q/xj0SwkLw0Mg3DOtRjeJAAJ/qEdzJ/jSehhb",
              "previousCounter": 0,
              "rootKey": "cvIYipBTQgF/PbxnPaaR8JkZLUJf5EJDyZ6BZdCyhw0="
            },
            "indexInfo": {
              "baseKey": "BSnSXwPlFucsvHCzqECLOQVM9Bit/sU6UWEEepgYTsJj",
              "baseKeyType": 2,
              "closed": -1,
              "used": 1656088016482,
              "created": 1656088016482,
              "remoteIdentityKey": "BZz+trlAihUDlXb/ZNIhZ+FTbNQucFrMjWB6kM72eHpU"
            },
            "_chains": {
              "BbjynG4Q/xj0SwkLw0Mg3DOtRjeJAAJ/qEdzJ/jSehhb": {
                "chainKey": {
                  "counter": 1,
                  "key": "C4pXS4zmKCQxzIgbWdbxCF9D7et9qqtwxQmH4pN37FU="
                },
                "chainType": 2,
                "messageKeys": {}
              },
              "Be8h21fUYM1FxSXWO9pZLDME1jhCzN5FVvML88txXJka": {
                "chainKey": {
                  "counter": -1,
                  "key": "90Skm1n8hpkxLB3d8YJI1fl2TtJ45Grrz5SH62Rw8FE="
                },
                "chainType": 1,
                "messageKeys": {}
              }
            }
          }
        },
        "version": "v1"
      }
    },
    "appStateSyncKeys": {
      "AAAAAM/Z": {
        "keyData": "1uYcvunn/tAxlH6ui8Ipmu27zy0Y40QtNEvKzvNpnhE=",
        "fingerprint": {
          "rawId": 224368714,
          "currentIndex": 1,
          "deviceIndexes": [
            0,
            1
          ]
        },
        "timestamp": "1656086994124"
      }
    },
    "appStateVersions": {
      "critical_block": {
        "version": 1,
        "hash": {
          "type": "Buffer",
          "data": "VTHUucPpcH+o0Xv698Wah/yw9C5ML0OK3MS+k6AjV1s4BlSA26X00Ck80cvIgsztrzhZZZAisqQNBYSqg7X//WRxI70j4Qut1oRuoEI2gVriuHA6WnUKJmEGlKO4mnXQLWX3A0jmMxEEZnw7sEpYHOL2GEhd5LnSSy4utj41hlI="
        },
        "indexValueMap": {
          "pUZjsWPm3XL+uLydWDkzbv8RVxTDY5GiL6/GPE0NslY=": {
            "valueMac": {
              "type": "Buffer",
              "data": "1qQj5lVb9rcV1QjE/M6X4o7dohXikVa4Vb946reeXBU="
            }
          },
          "xbqKp98HJA4WMmMR/2wNeh0xu+E9Yqp9Ot2TUomarzE=": {
            "valueMac": {
              "type": "Buffer",
              "data": "8DD+UTMxCSiDf2nKz+c60dAIHBYL+yEv5s1cwWHwT1Q="
            }
          }
        }
      },
      "regular": {
        "version": 1,
        "hash": {
          "type": "Buffer",
          "data": "yjEL5800kAKmXWmOLeoxtfcEjVWIc5EYIgR1eAtO1myLs2fBPS6jAXP0KfoF7kaS5fDUFGd+hzetGYuFTaMVh5sERoIzBYok5BwBAKIDcx8ZFWtDLFyPnuM0GVxOX8PA2CwTSkoHpBun75fBf+Plp5dEXZaWfJyojoXksrOHv8Q="
        },
        "indexValueMap": {
          "7mpORFEGF7AWiD23wQxUY7NTfQ+9Fxh5eUNhNDErb/A=": {
            "valueMac": {
              "type": "Buffer",
              "data": "Txuw1NzCIKMGI3KMzgK+I5wg9urgJyf/pT1gSddVM28="
            }
          }
        }
      },
      "critical_unblock_low": {
        "version": 1,
        "hash": {
          "type": "Buffer",
          "data": "i9W9vOJLH4uNvNuCSv7t/i9lhF+TkXcBxG1QNG8ecv9d0uEk4bVy4BurhI2UPAjCqmc/7jv8prcwZHlyjjg1KOO9mX5Q5YE8/k9UMceYaRNMRSveYmmbYCjuMIryEZ1LpueKG3bTN9y/MNL9hdel+PP0E26LrjB/gZNGwvJXSFU="
        },
        "indexValueMap": {
          "wqEwakdT76/OPbLbSM8EezkHJyvHwH81fszufJyE1Js=": {
            "valueMac": {
              "type": "Buffer",
              "data": "KGuDaTgFGp5DD8uWDE55jAcEI3XF9Mu09CCS2ZdhL4w="
            }
          },
          "yWviuehnhRqTvw+huzspwFOFP1RBFGKvQbJYkEEDoVE=": {
            "valueMac": {
              "type": "Buffer",
              "data": "MLTTjqZjh91wu09MPECxK0NaJBKApK33mgcDntqM4Dg="
            }
          },
          "7uQNrZ2F25f8Vrs6P9cYhD7jUbwNRyjvJ/vL9d6dL3E=": {
            "valueMac": {
              "type": "Buffer",
              "data": "BJF1LLnMFEcT2/e5g8NfiPQ8JxCnqm5ELAZIkxFio8c="
            }
          },
          "ZmmIGIx+H73/jHNXuNBO7gL/S9OpgepQ2/C9qnNskNw=": {
            "valueMac": {
              "type": "Buffer",
              "data": "U9FRJUfZ/GMzeyHni57XOZ3tPPMl+CNOIQ7oTul8mkY="
            }
          },
          "r2umT2NOJZviXA2f5z99q+qzAL6ZomxPmdwKKYB2vVo=": {
            "valueMac": {
              "type": "Buffer",
              "data": "ccZ7JqKiG6GKw4wgTeXhXkrT2ry6zRjPOZMVQcRjhrw="
            }
          },
          "cwQqe40O1v91HiHLUZBQ3TzHzS++XnyGxzMnukvPi1k=": {
            "valueMac": {
              "type": "Buffer",
              "data": "QE54msBOjuGWRc9CNFtqt8utvYHZTJkWe/f6WfjnHIk="
            }
          },
          "vAFBfMczejw785kzwogPPj+Urx+M65U8/W1pGFByNVs=": {
            "valueMac": {
              "type": "Buffer",
              "data": "4NIr4UUkbs8KMcI1ZBaAU3p2XsXSWtDO4+QwpU5cUP8="
            }
          },
          "tX5Hqgm/Bvh8Tt5dcMPy7CX4//wIwYIGCa3uVvWGvtk=": {
            "valueMac": {
              "type": "Buffer",
              "data": "eFwr1yj5fMVxAV9DycrFDPCsjDHvoK4PZotR3J3lknc="
            }
          },
          "n+06HChF9odctbzW70csYjMmlieIQ53NCs5yyNFlngY=": {
            "valueMac": {
              "type": "Buffer",
              "data": "RGywdf++FtYcIALS3i3cs5T3dbegkx2/PX5ovSLGMuk="
            }
          },
          "ieDoV9Cpo0YfJC0XVRxrJ3eFrHwSZZcFcg5zzKbhirY=": {
            "valueMac": {
              "type": "Buffer",
              "data": "USlqlhcLoPAyW0thbrnuBigEWSyWOo8pd/VBDAMNijY="
            }
          },
          "qNgD8MzY3BL0v9tn27FUjCUo+617wYUD8gnd1zp4/VA=": {
            "valueMac": {
              "type": "Buffer",
              "data": "+DRQTsKKKEoCqapAnd/hiQ9N0xN00NZld6zLrOKUnRk="
            }
          },
          "G1MeeoUuOTLv3RbEaNX480JfcwmMbNcpyv8XHxZCUg4=": {
            "valueMac": {
              "type": "Buffer",
              "data": "FLHlbXKcwzipzX5eVNT7zosbW4AI1xu8YbeZN4zB2hg="
            }
          },
          "6SVUc6cE+xZdGC0gMXIzkznFxYIVfYle65q28gZ6nmY=": {
            "valueMac": {
              "type": "Buffer",
              "data": "RDl3Mo4wLY/TOoutaZN6AkNgNqSXNWcm+ROK5JZIEzw="
            }
          },
          "6WUKTpuOvCZJ1AaXFrsD9jJUlQZaYNFzh06iyD22l3E=": {
            "valueMac": {
              "type": "Buffer",
              "data": "OPZ/MG5HckffdALJ1DvX3w/xQeczJs/Snasjuo54Q2M="
            }
          },
          "HiNk4UpEuisGB8sykd+BIlJM3cyvQHgEn+ZOZTS8XO8=": {
            "valueMac": {
              "type": "Buffer",
              "data": "u7AMNYiZp419LPJzwG0Ev3fE6bjrXFQHsgQ0h74vBAE="
            }
          },
          "Hmi4VXuYTgSLlrW8hakncEf1gMbMl7Q5kVwSUzrvO/g=": {
            "valueMac": {
              "type": "Buffer",
              "data": "dwIDW9FWmlJiXqKGiQowp2ODeOE3A4VwHf+WYyqpH3A="
            }
          },
          "CvVc0shtIpQD1o2Xr3Ur8nX1TVx2id2vUNrjXdaWTrs=": {
            "valueMac": {
              "type": "Buffer",
              "data": "aXk8UL1OGaUdl9D0JSa/V4chuYHQlTfRWg0dq1Nd214="
            }
          },
          "SAxVvE+FXX1orlKtcDmAu+nFGr0/HUIfe2UacA627G4=": {
            "valueMac": {
              "type": "Buffer",
              "data": "TzEvjPPNUy0DcYOIACPYqQPUXZ8nYqoYy9WT0ytTkTU="
            }
          },
          "xpGpKMW01yFBmIEEe6RADQMs1GtLxd5pqOnNDOTX4qY=": {
            "valueMac": {
              "type": "Buffer",
              "data": "qtrPnv4jZljNp/QbhVdOfSCEoRLejjfjYo7KpcGcQoQ="
            }
          },
          "lFJgu+zxFLJs/joPOpu1x+OyR7gtk9DNYa8YulBv0/Q=": {
            "valueMac": {
              "type": "Buffer",
              "data": "kBpw0MVU6OWBM0AaqB+EhGWKVMUSJ57aYKzM9cFyfz0="
            }
          },
          "8FNXfARHG4Kbdvk/5DiMVhoyfZaowtg4EpCCn3QwTwY=": {
            "valueMac": {
              "type": "Buffer",
              "data": "YxkaQwGxo7kg104a4/Q+YDK4ETPO6LoVQ2o8YtM+N/w="
            }
          },
          "g2L3SygUOT6nkARGB1ArLhAUGASIZX4WPnaBeplpssU=": {
            "valueMac": {
              "type": "Buffer",
              "data": "mOpnGLq87b8AfiTTOhlWuyyZ2pc5x5cX3On79Suq5Yw="
            }
          },
          "dVUCo7ltj1kuO0DLxM1G13MYGE1GjdSS3LyKUphX6aI=": {
            "valueMac": {
              "type": "Buffer",
              "data": "QE75aZyrUzVu9ZJL4DgVaOQE1b3C0f5e2i65ezKhK48="
            }
          },
          "0gqwh4F3v1Yr1v+8+NwYfIKqWQofdwvHG4KV9DdN/68=": {
            "valueMac": {
              "type": "Buffer",
              "data": "iGXd16us7mR7dRyGmdXGMhsaW41Cq3+Y1RKhVWmK0BY="
            }
          },
          "Nb4FUNbKEt9H6Dyi55ygI6chQhs7rSlOld3bXq2iSVk=": {
            "valueMac": {
              "type": "Buffer",
              "data": "5jj86oOATMN6hQuuAq+0XQLEAX4UCElyTBXo6zZRftg="
            }
          },
          "8IUgXAcRxSpSoGBjqhyJ6+ylA3RuuMp6YFcTNWBNMjc=": {
            "valueMac": {
              "type": "Buffer",
              "data": "9beusMcRwmVa1Gx/qmLBOvbhu/WWbKV1oPzHzjBajp0="
            }
          },
          "DorPeccFonRjWVEQzMtQwv87mlXtSgMlvXLGuDbrNeg=": {
            "valueMac": {
              "type": "Buffer",
              "data": "IGvDpRRukIraFJtYJ6VChkLBk3sj8ylvF4YjgziXifc="
            }
          },
          "+/D5ln6TddAUxd15TjxCg7PcCO9J55Yqmi3z2ERAXIs=": {
            "valueMac": {
              "type": "Buffer",
              "data": "QEfBmhBInmgASIWMy3htAU3Bw3H+PiRasPLgD/vxWTc="
            }
          },
          "04SGPw/F7DZysVZE7418RCHYwiIMFVY/Qkyh94VtoBY=": {
            "valueMac": {
              "type": "Buffer",
              "data": "hWc1mPqf7ai9NlaHSDETcztIzf8D9zLfTzxb9TL4luA="
            }
          },
          "MBPnlQXvhX02yLUADuR8AckX4Bg6Javfwt09KUMLcqg=": {
            "valueMac": {
              "type": "Buffer",
              "data": "pA1kN7lHGgBS2DzlTz9XWtJUr7zXWLTp4mvcTPiuArU="
            }
          },
          "xdPR+1t9G8Eu/nNMRUnO2GmJUjavaV2Y7Tq/rsRiSfY=": {
            "valueMac": {
              "type": "Buffer",
              "data": "yIlz0MwYlNioq+3AQGQvMXuNHXtGCDwxCVwXQeiVcJk="
            }
          },
          "EV8/eRGTnMZlvA42dSvEfmqrAIoARFC/Fi93VKxYfX0=": {
            "valueMac": {
              "type": "Buffer",
              "data": "U049bBQSU2ZwaFq45u5ejKP8hVIQRM8iQEIhHdQR4S0="
            }
          },
          "y8s7w5Dis5aOLSNuIpJLme/AQXPYlMRwLwt2emUl098=": {
            "valueMac": {
              "type": "Buffer",
              "data": "f6jfp2ZT8E2z3AsfLZqRH2lI/VduaT6eEO3AZwyo5eo="
            }
          },
          "7/mavmLPGrkuXztWUdO2RswSSenvMMNvVrb8sZZAYYk=": {
            "valueMac": {
              "type": "Buffer",
              "data": "MumzfedgxrEsmHvQuRoK+H8yyjDdWqz8F9/l7r/PS7U="
            }
          },
          "BHt2l6U2GCyGIWyWYQnOrYB2VCo5HoBwoUUazdTspb4=": {
            "valueMac": {
              "type": "Buffer",
              "data": "2O+WnWzMxpe4vT0i0LbkcLaTxNp/CmuCbbfwRWE+yW0="
            }
          },
          "fzqZE27dGv/5J0s8ButuBKrlHK5huh+0uy2cR6s4rP8=": {
            "valueMac": {
              "type": "Buffer",
              "data": "5PGKQdmoTrp9C/XDPKrriztQ5U0jZHZTfzlVqZsGAOQ="
            }
          },
          "tls+wIJqG+dVXoBtQIpmjSSQSyKRBfOQF1CR6hcNnZ4=": {
            "valueMac": {
              "type": "Buffer",
              "data": "Xl4Kb3o/WrvDQK/1EiWUWUd84x/DWTFYZxhsUJJu/ds="
            }
          },
          "Ylnc1HOS2GBJmGa/5ZxuydmWHnl+2jWrJ7iQ4RE+tIw=": {
            "valueMac": {
              "type": "Buffer",
              "data": "lqmNBshWb1q833sWM6W08lRFJ2f50yy9lElU+Ij2KyU="
            }
          },
          "1zn8j25BSlSpO+Yl9ARXVn2v2nbqwq4NUmMpeoRxZ6w=": {
            "valueMac": {
              "type": "Buffer",
              "data": "I5BxNAJyDdvGDUwoRUamG+xVLJRgsvhcxy+5jXGBkz4="
            }
          },
          "3Fi8W+m2KrYskhnz9MychDl0dj6f4iB/zblXn4+84O4=": {
            "valueMac": {
              "type": "Buffer",
              "data": "t1g97T2iQvb0NKMYEJgBi5GVgP84Gxky7HaZGKrhkps="
            }
          },
          "MS5LNcKz8apzfRS2uT9IRbdsJKi/JNcBUA8Uoq92gaM=": {
            "valueMac": {
              "type": "Buffer",
              "data": "Ip5Mjj4Pz9goy+iYxfx6N01PX3dlawRJsYka8BBC+lw="
            }
          },
          "7JTFmsLtPJ9agoNXhdif18RjjQ02Gk4MVEgdOVU1HbI=": {
            "valueMac": {
              "type": "Buffer",
              "data": "lcwLLrsbyK+efvxz6WM/YPFaG7zc3CMxFHN3qWKK2VU="
            }
          },
          "HiAPYla6wIFBwmv77YYTWxyd6OmEtAgPetPL77WcuEY=": {
            "valueMac": {
              "type": "Buffer",
              "data": "8C1bYtl/OlJJRLS7JOHjs7b1UfmkSSHTOzW2Ap5XuCM="
            }
          },
          "/xnwoEVTpskYB1ZasSQ4r+k27EIJska3osfony/fZIY=": {
            "valueMac": {
              "type": "Buffer",
              "data": "h6P1FQVnozBj12YgQ6a3CRg4uunXkzxvuzqBxaT8/sE="
            }
          },
          "iiiFoL6cOQ3exFePAifNtPcJACubkSTEt3VosmczlL8=": {
            "valueMac": {
              "type": "Buffer",
              "data": "Fu6PiL1guf973OHOLMSIZIbvT7wyxH0UdNV7xFUTUBQ="
            }
          },
          "EvJrOBWYyk0f288Fs3CtZXCbWJ9wvTU6A+WuKMx1zEc=": {
            "valueMac": {
              "type": "Buffer",
              "data": "b1Xd94qnphd6lgwEKz6k2txY9tgeOl4kVTNxy2E/HoM="
            }
          },
          "G+ooGmhjNzEBHMgE8L8hl286urHRYUofKYDhcxY+8bU=": {
            "valueMac": {
              "type": "Buffer",
              "data": "ac+5zxFVmqYJbNRVGikZZej8ukZdmdhPu3sKlWEJNiA="
            }
          },
          "kg08aK4bakg7pG3rqbIwnPrz2+DaYBmjIwiKwTOB4+A=": {
            "valueMac": {
              "type": "Buffer",
              "data": "cMhP9xAbjckAJM8ZmXtwhS2JVpsnrTHW8Pva8bwqN7A="
            }
          },
          "gaWENbQeXeBHngKMhUx/Lb+szmm1rS4HfW1x4tiGncQ=": {
            "valueMac": {
              "type": "Buffer",
              "data": "pTcmC16/SMtmskCfXJxu51Olel8G8U5EZdRfn4T6L9A="
            }
          },
          "AH7oXrMV0odTSGg2omIrYkRtrIk84G5IQOkUdunQ94Q=": {
            "valueMac": {
              "type": "Buffer",
              "data": "ke+ryyat7BHNGLVu+cDxH0Pu6q98DWLwewq1Klp5zj4="
            }
          },
          "tTUmJ42IV/aXaLnlqDjeqTC4hny+GfjOVMH8Wis05CA=": {
            "valueMac": {
              "type": "Buffer",
              "data": "jOaqdqi1UZ0ZHSMTfCSyucGgKkLSJx8IoSlkLtdx1Tg="
            }
          },
          "Pd7IB/tj45ObVMeHG9Gysw0rqViVLbY8juBcxSav/qU=": {
            "valueMac": {
              "type": "Buffer",
              "data": "nDtHAnlP/yJravrExPhBXxdEUSg+em6l00MskUwNbCU="
            }
          },
          "tFMbuCoqtT+DZYYZaLXCOLEbCFOrbJQjMP5maKTON38=": {
            "valueMac": {
              "type": "Buffer",
              "data": "vJq9LGwcfTBN49htlsAszAEEuInhRUECO6eOoKcUuws="
            }
          },
          "gPb6ZSeWTH3PnbZNUHu4b6E6hNFBJGb3eMCmB5LFKY8=": {
            "valueMac": {
              "type": "Buffer",
              "data": "LFF4NUEXTy/ksqd7KawPZdrXo9Ih+dbNK01r29iB160="
            }
          },
          "EiHpeMKKXzyqKVoG1xLA1FbCdPpjw8kdFCy08pDYqyk=": {
            "valueMac": {
              "type": "Buffer",
              "data": "FeEnNe7e2YOkERIItK/hhSheINTn9IKGZSqKaSABqP0="
            }
          },
          "3C/+VoJ42kjq8w8Vo9EWnbzDzP6YkwD23vZbFbU/WAA=": {
            "valueMac": {
              "type": "Buffer",
              "data": "XIodcQFE0w1zaaJAPebKm91Y/UOLTUJ6t+pH0EvAWgw="
            }
          },
          "79ue7bGrNIn5BFaWEPTlsyx+VUDbgIZDUUsuavG3eJc=": {
            "valueMac": {
              "type": "Buffer",
              "data": "XhxBf+iHDmsllQ3PnVwQbwlycdyzba4oVonrvJDFSXk="
            }
          },
          "8ZghvszHH7UTnhU/JDggq9UzT5PtW4gYO1dSDbO8jmo=": {
            "valueMac": {
              "type": "Buffer",
              "data": "BuxDie+PucviAh3wn/L2nH9U60Y0+VTAGjGyRT0ilCU="
            }
          },
          "+AAixaOTinj3lYTm224jcM2THAv/GFIPFYmZRmUtHwA=": {
            "valueMac": {
              "type": "Buffer",
              "data": "XhdSw5gDY0cudaHHo9uDh/nay9aUpBcvi9+CUyJGEpo="
            }
          },
          "bQ0gVkJQsfx0kon4Xrjliv59oHUAOjwWF7cI4j/glcQ=": {
            "valueMac": {
              "type": "Buffer",
              "data": "yM2J5MXaRMrtKyOgrQsKUklcKdnGiJcGl4EP1MBCXrU="
            }
          },
          "yntIteNEf7bHHYkwNFEMOBWH8DBM9s3ivmZqhH8f7vo=": {
            "valueMac": {
              "type": "Buffer",
              "data": "0NniSxlsK6bRiC4d0QkWj6vlhmcc6s+egIsu/SNPW9E="
            }
          },
          "vXupVGCWQ8K/W+iP5SMymN8VsM7pG614BOFGtS5Znes=": {
            "valueMac": {
              "type": "Buffer",
              "data": "c6QVimhhhOlo3M1/TB7KqWoq0U50GQxDXZoANSwC3Ko="
            }
          },
          "QHfTpxozc6s9BuShcJVoGad4B3tdzb4zxucXX+osILc=": {
            "valueMac": {
              "type": "Buffer",
              "data": "Rt/eB6Ym7iRxHZgqVLWPUaFVvu87PZn9E1v7UvK7Jz8="
            }
          },
          "0E3zEjiS1ItDMUzw2brql4F1itu7d+6PWkh2nFFfgRo=": {
            "valueMac": {
              "type": "Buffer",
              "data": "32fLhnAKhKxFp5logoePXj4HnRYnvWxJHRVyXZpPMpE="
            }
          },
          "fc3cMUeVcVLzIJI+ua9ki/I3W8i/BCnT3Hy2FEb1z1w=": {
            "valueMac": {
              "type": "Buffer",
              "data": "g7+XTFGFCJoxYgx7YAc2cMby9Yg9+mRl/6AfKP4m65s="
            }
          },
          "wn4eahwEiku0dSVXEqYAHuPpEP9UEKVJmQElVPJzAjc=": {
            "valueMac": {
              "type": "Buffer",
              "data": "uChOM4KBmeybDGyxkge/OGuXscvbZPJJ+l2gEQ6VTEc="
            }
          },
          "3kuTLjPk4PI4wwsAYXgGgT92T4DZIA/wzTVEt/OW8vg=": {
            "valueMac": {
              "type": "Buffer",
              "data": "2U2dIANuW33cgPdRT2EZ4QocZbLokx8Awt+hn1eyDPs="
            }
          },
          "a/Y9buk61HqPKbu4ENgkBE5EHuwKaMeJaFHNoAXLOOc=": {
            "valueMac": {
              "type": "Buffer",
              "data": "CmTihuXJFKF0okZAEuPRTffKjfJn8CzdiJPCBTcfBSs="
            }
          },
          "N2piffy+D6NcHOIFUR5vSHmgaI4vrowO4sGnxti/R7E=": {
            "valueMac": {
              "type": "Buffer",
              "data": "Nys/aO1+87d102BLJWezwpZMGb+XzsDybXv1Lt9i+HQ="
            }
          },
          "/pIHUm8vNVzfW0Z4/eFDqzlQWEMLFX4zBbXi/cBT2qg=": {
            "valueMac": {
              "type": "Buffer",
              "data": "YSOXRa4s3HZxfVV4VUHaJFaplwL3M2Nt5vjYFR3/NKU="
            }
          },
          "/ogikIPMfFFGF3RFBg9ZI0pCIJ6TSYxg28V7lxgKFNY=": {
            "valueMac": {
              "type": "Buffer",
              "data": "9Uu+8Vc/5jR3lkk62VKvi+lKTCLuQiqGJxojiA+d5iI="
            }
          },
          "vOGtMnZ+d56ZWuURaA+rK1C1GRxZ6QXxzcDOcwYh1xY=": {
            "valueMac": {
              "type": "Buffer",
              "data": "HyvjyydvaMjhN8U5zSHunWWsdI8yEaf1bUpsh3ohA2c="
            }
          },
          "dULgTdsRvsnaKOoUiJ+qKrDqOSHQbspf57LihsOjNxI=": {
            "valueMac": {
              "type": "Buffer",
              "data": "Dg60gzSfEVbAJLHvf9IchztmzntEEshnoIbp4xMHpHk="
            }
          },
          "l6D/pJ3X7BHlnsJ/mWDleh2SnpeazR69sNdbcxILsqA=": {
            "valueMac": {
              "type": "Buffer",
              "data": "7pp/EZIV3tS9/GXqcET4xyQLlQBn6PxCk7nZuvubbJY="
            }
          },
          "DTbvcHp2zlLgL2hjosPGcuTXFlaczcbB8PaulWoLZ1w=": {
            "valueMac": {
              "type": "Buffer",
              "data": "AUQ2ox8Z8q4yiGsIu1v356MoHzGa6xXWbXgJkXqdIHY="
            }
          },
          "xWHNKGOapyHBnoSqXtfvqGf3A0OX3Zx5H2o7EijqLFU=": {
            "valueMac": {
              "type": "Buffer",
              "data": "nnQUQt4+yAIwRQDn79qZEhlGIx2djq4IMksat5Ke2o0="
            }
          },
          "OrjtYNJt/oo7f/pX8+KOZKyC4shzNN7vVmrcGif2Dzs=": {
            "valueMac": {
              "type": "Buffer",
              "data": "euO+IDXroKwvazD+Y1AqG766OGww+JLHBrM1j5vkaNA="
            }
          },
          "KCFYCWvrbPhNnqhfzl82J6UX9Ir9V8D1HhPBnHdPGDI=": {
            "valueMac": {
              "type": "Buffer",
              "data": "cue1r/bIUod8RILKKY9yUiU9tk5WFuhKah1ahHyFWEg="
            }
          },
          "crh8OPKdUzPXOSHY+HPR6f5A4v02aVOj8iZqB48LtGg=": {
            "valueMac": {
              "type": "Buffer",
              "data": "GihYi1XJDChFLk59uhe1HsUCAI3OQ/UEZ/DhB8aMzyA="
            }
          },
          "g/r4xREBjjCnX5qyCkdI7Jl8xwAALkuLg5AlBPjOOcI=": {
            "valueMac": {
              "type": "Buffer",
              "data": "wMNVv+KWG0UCOu3+FCuKBndV8ykKN89MV1CPyAx7nKM="
            }
          },
          "JJ/VTrtXVn39Z656XcSznWYUvEVqIXXtIp+E5DTzI/8=": {
            "valueMac": {
              "type": "Buffer",
              "data": "4aaFJKTPmF4DFBRHTs6tLTIfAhq5nT7PrSnHL1q7Jro="
            }
          },
          "nBZrLcBNyNRo6+b//as7D+3lSuG2IsKzeDr5DZnpMHQ=": {
            "valueMac": {
              "type": "Buffer",
              "data": "zP7CRmQrMFRBjlYJiiMgsYtj2KSt6Png5NALQKZmH0I="
            }
          },
          "0iaOpMbON34yhkg6fezNFbY8FxLgwtHBdV3XTG9HeMM=": {
            "valueMac": {
              "type": "Buffer",
              "data": "gsHCUBk4lWGBNypVZihxl0NHjnmBxNtW8Wdpy5iFQB4="
            }
          },
          "tv87fqYF/NGAmuHwA/VXnaqCq7ImGzwwrkaipOWcZdY=": {
            "valueMac": {
              "type": "Buffer",
              "data": "Dih1qg3pen33sP9EAOx9xHbFpAgyy+khCRTmSN296Ss="
            }
          },
          "3B3ZUXY9nNzR+PjGZAIHF1AZumuXpuv/DaLuJ052Ig0=": {
            "valueMac": {
              "type": "Buffer",
              "data": "DJ9ywtz8iR/Dy4+r+xwIs7cfnmluvkwYeYa/g/stGzg="
            }
          },
          "VhasKE8syb7/u167EDDY+aY1NO4ohnrMw6e1yh9xJ5g=": {
            "valueMac": {
              "type": "Buffer",
              "data": "jJ+snDI4pByXsEGkI8KLNZwaJdrg9l/9GXt44si62Qs="
            }
          },
          "HpMltX888u8wPKBR4sg618MRuScKEpaGqOGPpDUOHAE=": {
            "valueMac": {
              "type": "Buffer",
              "data": "NPwU2P4aBaDOZVQAdbCAd0tsOoIBQlaRjdyaMLi++Jo="
            }
          },
          "wej/sBbZnua1+FVw5PgRqBHA2jRiHamYRoRnlPPfKNs=": {
            "valueMac": {
              "type": "Buffer",
              "data": "mKlMYSLZqDiVVOHs9S8+gCO+cUn/EgbxmpJFSgPj4Cg="
            }
          },
          "sP2acvgwDiwiamGHQTF6cjNBDOnahkjid2xTKfaqX6w=": {
            "valueMac": {
              "type": "Buffer",
              "data": "YwWZ1YTcSQ1iRIzICcb3UeQc2HYJw8Ry91mdANJRA1g="
            }
          },
          "PCkBy2Cd4n0gAr7KHzZIFd54lhU7I7/Bia97s5ML0J4=": {
            "valueMac": {
              "type": "Buffer",
              "data": "saeTmXfvxqYndzCvtBvYONUNvvwZDP9Z0F8pL8KltVQ="
            }
          },
          "KB7DuX0LqD2qDJP74UPnZIBG/Iv3y0VtOWmexvr8jl8=": {
            "valueMac": {
              "type": "Buffer",
              "data": "x1s1QtdYyDGnaCnQ+JenV5Z5+WzNioNCU2bIuCd4MnM="
            }
          },
          "0JSr4fAVBJOVtzL8MabemwhH/Eeh1p7ZnimWlulfAXU=": {
            "valueMac": {
              "type": "Buffer",
              "data": "MjcB+nskRH44GIkLe+nVZxIcwniOJAMAwTYH5GtvgKs="
            }
          },
          "VkoRetR/+J8Ixd3st96EwRaXMagvV9fdL3nUgLosTxo=": {
            "valueMac": {
              "type": "Buffer",
              "data": "vt82QCj8BcbFTXAqpgz4M8lmbSV3UlBdywaj/nYTAx4="
            }
          },
          "pHJieuOEmcM0Vjj8RXK/rTQT0yR2JSGGK1eR3eSxw2g=": {
            "valueMac": {
              "type": "Buffer",
              "data": "TWgfe4nNNOvADjTCuGNT72EodbwqbLRn/mgPyQ7kl1s="
            }
          },
          "dY8+HnzF/WCoBAFG3uVC90ybs3cUjHynpAFZg8rzDl0=": {
            "valueMac": {
              "type": "Buffer",
              "data": "AVlY+ZC28QCpKvrKGNtgKl8bwvbKcWDBE0xVlEUVeFY="
            }
          },
          "JIV5NgclHIM4pRJUCohZuWaxNq1X50UK6Yiy+JLGK/4=": {
            "valueMac": {
              "type": "Buffer",
              "data": "ekBPTD4qfwpIo5YrAR7qq1PDUBGq87vREOU8NnHmRIk="
            }
          },
          "t49dM+ScUPzpvCQzhiYyUWuMWwECqI+RAd1sJBMrGH8=": {
            "valueMac": {
              "type": "Buffer",
              "data": "9GwOWeY98Oa8vltKVMUJHAYNk5tkrYnxfeedOdiKLns="
            }
          },
          "hF06MHJdeiu1w4yz9bcxXPrrcd2zj3hdH0kNLHhftnk=": {
            "valueMac": {
              "type": "Buffer",
              "data": "qKt7WeUXsuxz3so53HNfyMRhSv9WtfikOvYZO85KcDM="
            }
          },
          "FlzKiEvZpa2YyD01BUJc69vfxDR77tuN0lXvrn6gmi4=": {
            "valueMac": {
              "type": "Buffer",
              "data": "jebFZmW8acJo+U0N9aTu7DGFdnYyDjXN8NvuswcYTVw="
            }
          },
          "n+K608/DvhRNXvQPSK0JsVl7sZYNGTbH80MLzglWQGU=": {
            "valueMac": {
              "type": "Buffer",
              "data": "wiD+pgVHhtbxStl6pXuUg2x1u25aHH5V/a9dT9GHEb8="
            }
          },
          "poP4tQC/HaiAx2nX8RqBfZrKr4EY+COgmpTzzSgJwzw=": {
            "valueMac": {
              "type": "Buffer",
              "data": "Ur4lXzx1z3XZWaaXe06PcZFTpa+kUMODjqmWMMqTRy8="
            }
          },
          "BwEkYLf7cOhmiH5ovO0nokFgTghWUiU7b68+7xITRJM=": {
            "valueMac": {
              "type": "Buffer",
              "data": "xLVrpvwVJHGCVBQb/4mD0JQ4inP2o4c3hYTIUPoJYeM="
            }
          },
          "bSPlqh1x3YlGlChmTRnmSpPOHepQ7YDb4mu3+yo1YCs=": {
            "valueMac": {
              "type": "Buffer",
              "data": "zfJfhzF1R6Omn80ptgRdbsGMOuekdZ0fdm50DnHIXuU="
            }
          },
          "R6u7nPNNvz/vkGkh6MatiryUdsXMiqN6u7fGH5yuvhI=": {
            "valueMac": {
              "type": "Buffer",
              "data": "WXtLoRM0D2fe0OyaEo/KEJ/K69g86Lg2CUsh8Uviukg="
            }
          },
          "NEJh4Y4WdhzNbnZkcre3vtVostnQE2PS4fffLVTg1Yg=": {
            "valueMac": {
              "type": "Buffer",
              "data": "6FEFwCdS7yqY2jFM4iX5+gQGZ8y7GQCtDg2zKCQpOmQ="
            }
          },
          "laMNIOseBEsT3zolUChLSX7IxdgBs7j+H4zNaBHvB0k=": {
            "valueMac": {
              "type": "Buffer",
              "data": "1ghcmHbJNZ/yQnrjgKH/Ho/BNR1sK6MLIvDCItA/iuQ="
            }
          },
          "9VIqvXVeCMgIEWpuYfkSVYR58zyoU1/g6sz2jc2oRLY=": {
            "valueMac": {
              "type": "Buffer",
              "data": "BtjdOGlV3P44wmnH8t5DKIrVwKIhBlwucXW4Lt2Bc60="
            }
          },
          "0IgYar+VUkxLVqCU0MsaX5rEc3HJsGeW8rB6VVxDedM=": {
            "valueMac": {
              "type": "Buffer",
              "data": "tzvQDp2KcugfP/MbToeZosMGUwF4/VgJwb3wSUj9orM="
            }
          },
          "ZIUUUKStAiqadFGZXFa0ynWcoXO7V+OmlPbVWaknFYw=": {
            "valueMac": {
              "type": "Buffer",
              "data": "ZV3tOBBNWsCNew+tEwfwgpxm7yz8LfeQRu812paNgt8="
            }
          },
          "dIQAiUGspPyB4CusrQAKF5aznxXz9/7BKrCGqFiqhq4=": {
            "valueMac": {
              "type": "Buffer",
              "data": "XR7DSP3h9DEJBzyetNoT+wDZc1J+ywfVwsKmACiXGTg="
            }
          },
          "uehUlsaxgYCVM2hFWVcMhXZVN4PIImonoYoJN6P7uas=": {
            "valueMac": {
              "type": "Buffer",
              "data": "SRd0xppbLbtFQbxgPGmF9s3Ak0tL/czBJARU5xiEwMU="
            }
          },
          "IK3Dgyc26Luo6cXleHdxV3YEGmomJ5zE6hCqcVJm6jI=": {
            "valueMac": {
              "type": "Buffer",
              "data": "PqtfPpCSDlFOJzl0dWfHe/RUup/hPP3A2P9eqPY836Y="
            }
          },
          "TCyMOGFH65v8Bu8DpOu7/Ju0YsDwu9XBHK4PmZ82hio=": {
            "valueMac": {
              "type": "Buffer",
              "data": "q6OHcMeejjR8WHUFh+TSNp16qYMRr3EEkks/UdaV9vI="
            }
          },
          "EF+AZBfYcfwJ8MZVD0YpSPucDSe2wcZaJkGCB9zZ5vY=": {
            "valueMac": {
              "type": "Buffer",
              "data": "wC6L/KoVxf0M51yZNQCZB/2fvHY9K3lKkmFTbz1PnXA="
            }
          },
          "W2stjm8mtZmxQtppd07tJxxIh/MucePNMg6bCZsyQhs=": {
            "valueMac": {
              "type": "Buffer",
              "data": "X/knDXGo0UhuNcavGwXeGguQx+bO4t3G8za8i2iYPKM="
            }
          },
          "MeAe1dmEbEtEQpZpvlkMfJH0WZ1VcHalr3Zbm7XRowo=": {
            "valueMac": {
              "type": "Buffer",
              "data": "g3uXxnX4gys/zLCAlGsHLf3F1g4ertIj8Md19GF7eu0="
            }
          },
          "o0qgifsmDpkQLKxQAq0yQKn4CssNi5rk6Bk+Xn/eTfM=": {
            "valueMac": {
              "type": "Buffer",
              "data": "9gb9HupuoTTLa7MJ+6kAF1RKuUKcr4o/dVaMxvZz0YM="
            }
          },
          "PH8/aqmuSWhTvWZm2biEEYeZGieJP8u/2G9nPWV6mVw=": {
            "valueMac": {
              "type": "Buffer",
              "data": "BnfIJ6vGVF6oXaQ+voz8rbnMXV5H9mbxb8IZuslstY8="
            }
          },
          "RsME1Oo1RIQ7dO6pLiiVkevC9HPxo67q/x+KA4OXhhY=": {
            "valueMac": {
              "type": "Buffer",
              "data": "zhO5ZuS/RVwpQyaJkysm6jwdG1f9ez5UskNE/um8Y6M="
            }
          },
          "wI6QyJZESJ/V0XiAX3NnZ24nJ5D7JckTieYdIBFL0iQ=": {
            "valueMac": {
              "type": "Buffer",
              "data": "8+fFySCOAMZB0zNXUqxr9b+SoxiLxyDtDeK57DX/RQg="
            }
          },
          "1eOSAJSsWsjqdlwBAY0x9CqccBHYf2n5P7FhFGxUUPc=": {
            "valueMac": {
              "type": "Buffer",
              "data": "HfgUwGChjEJG0R7M++V74CHVs7DQ3+gSxedJIylv5j0="
            }
          },
          "seWDaIFPGJMapPxUm243MRZaSVIGf2QNedFANS7NDPw=": {
            "valueMac": {
              "type": "Buffer",
              "data": "5Q8umGlmbEl9sexWajQeiiBFgwrTphHCA46Il0VDlB4="
            }
          },
          "tIESIqlEEebKQGVHnIohGN6bSABCStXXpgD4KtR/fRM=": {
            "valueMac": {
              "type": "Buffer",
              "data": "zoL/lLlQ1HeHru5Aj0js6SRPp8cNg+e6BlAagfPp8r8="
            }
          },
          "M4sZb+JtfSBRsUAmzkFuZCf4FYGrD5sSRoJftXXRkIk=": {
            "valueMac": {
              "type": "Buffer",
              "data": "pWDTUGLlLzwv642Oh5TlMGkhNDZTc2orDiazeZatu4Y="
            }
          },
          "1VvFdDl49Ug01BtvYPqweYJgyvupSwJDqXRwDa6eblI=": {
            "valueMac": {
              "type": "Buffer",
              "data": "SecCvgbjxGBf2NAqgC0O9WGN35uB0i4c2kbx66em9NA="
            }
          },
          "KKKqiNyPozqhIv9WWT0xskb1lsQSB57e+kcg7g2cJ7A=": {
            "valueMac": {
              "type": "Buffer",
              "data": "h3UTXe1rO/B/6WQKjcj6XXWGR2aDWrd+jGjtVGQnf4M="
            }
          },
          "c0P4bXEFs0ncA9TG+Hb1s6NJ4DovOXX8QlsZcl05BGs=": {
            "valueMac": {
              "type": "Buffer",
              "data": "X6WPk7tBScyzCfwfqu6wBuaPf2z0E23yuPLvhdSn5MQ="
            }
          },
          "wHpEzhppZIeOwE303XpQCDrrbEjITTFLyvdrkXcYOIY=": {
            "valueMac": {
              "type": "Buffer",
              "data": "Sslo+0DLqODIa4bmE4o4yFu3sgu/HTX1fCrR1He92Qs="
            }
          },
          "Bq4Qf7+Emkjxy2MdlwsmtzBNAgHZ/fJKWsocqbMbRaw=": {
            "valueMac": {
              "type": "Buffer",
              "data": "b3hNvSwruuB7xxuC2Mr+KGJKci67A5ph2KX8GTNaK5k="
            }
          },
          "udtFvYenmX7SpuUABy1Pyumioa+MQ7ah0bj6A6/Esnw=": {
            "valueMac": {
              "type": "Buffer",
              "data": "v8Gp2kdS1bcQBM12KWiGEGFjix7EeKWGsyun0vYnZuQ="
            }
          },
          "8eSjZ7XP+BlqMVypOxdWgdxyYiq3gSEMMsfyTT8CKwA=": {
            "valueMac": {
              "type": "Buffer",
              "data": "PgoVrEEyPqw2LXxGlPx9BJAv9ck15SO/aCIS7eg9NJw="
            }
          },
          "Bb3gw119lctjsmvRQMYPsSpShqlkpjQ5Lh4286f28UY=": {
            "valueMac": {
              "type": "Buffer",
              "data": "IKDohH4jAHqDi3Acrp6EmvzsVg+cuIb/h7wkTUcNjHM="
            }
          }
        }
      },
      "regular_low": {
        "version": 1,
        "hash": {
          "type": "Buffer",
          "data": "HAvbU6gPVmW3v2wxjnTdki24sxJvCZXSU0CEGMo2JbqKsD5MP4PwE+ctMDhDivdS3d5q1AoRH0JXbXzrWQ8CwBfpkqxW0kH63FiYxDsfIohWVdO9Vh1i6xXXh8H/ogKXn/Lxf72RusgDdCXr5UQHBejf91twDkvP5PFzxShnelQ="
        },
        "indexValueMap": {
          "81dEK/Oag4DqgWxeirDUG8g4u7esin71HuNeS+P5wuk=": {
            "valueMac": {
              "type": "Buffer",
              "data": "cophaaiH+jltDRx/SYi5NN4zsUzLKVDy+iwonbs2E6Y="
            }
          }
        }
      }
    }
  }
}